{"type":"Scene","props":{"width":640,"runtime":"View/ProgressBarView.ts","height":1136},"compId":2,"child":[{"type":"Panel","props":{"var":"panel","top":0,"right":0,"left":0,"height":1280,"bgColor":"#ffffff"},"compId":3,"child":[{"type":"Button","props":{"y":0,"x":560,"width":80,"var":"backBtn","skin":"comp/btn_close.png","height":80},"compId":4},{"type":"Box","props":{"y":551,"var":"center","right":0,"left":0},"compId":5,"child":[{"type":"ProgressBar","props":{"y":29,"x":70,"width":500,"var":"progressBar","value":0.05,"skin":"comp/progress.png","sizeGrid":"8,20,8,20","height":30},"compId":10},{"type":"Text","props":{"y":76,"x":283,"var":"lbl","valign":"middle","text":"0%","fontSize":50,"bold":true,"align":"left","runtime":"Laya.Text"},"compId":11}]}]}],"loadList":["comp/btn_close.png","comp/progress.png"],"loadList3D":[]}